jdMrpackInstaller/Icon.png
jdMrpackInstaller/__init__.py
jdMrpackInstaller/__main__.py
jdMrpackInstaller/version.txt
jdMrpackInstaller/translations/jdMrpackInstaller_de.qm
jdMrpackInstaller/translations/jdMrpackInstaller_nl.qm
jdMrpackInstaller/translations/jdMrpackInstaller_ru.qm
jdMrpackInstaller-1.1.dist-info/LICENSE
jdMrpackInstaller-1.1.dist-info/METADATA
jdMrpackInstaller-1.1.dist-info/WHEEL
jdMrpackInstaller-1.1.dist-info/entry_points.txt
jdMrpackInstaller-1.1.dist-info/top_level.txt
jdMrpackInstaller-1.1.dist-info/RECORD
